{
  "errors": [],
  "warnings": [],
  "version": "4.44.2",
  "hash": "8338c247e8353c7b87e0",
  "time": 987,
  "builtAt": 1675795950210,
  "publicPath": "",
  "outputPath": "D:\\host\\MySPFx\\appcustomizer\\dist",
  "assetsByChunkName": {
    "appcustomizer-inject-css-application-customizer": "appcustomizer-inject-css-application-customizer_03f3ca85ce1449817c76.js"
  },
  "assets": [
    {
      "name": "appcustomizer-inject-css-application-customizer_03f3ca85ce1449817c76.js",
      "size": 2104,
      "chunks": [
        0
      ],
      "chunkNames": [
        "appcustomizer-inject-css-application-customizer"
      ],
      "info": {
        "immutable": true
      },
      "emitted": true
    },
    {
      "name": "b461bf4f-1e92-4dc8-87e2-fcbdec53d20b.manifest.json",
      "size": 920,
      "chunks": [],
      "chunkNames": [],
      "info": {},
      "emitted": true
    }
  ],
  "filteredAssets": 0,
  "entrypoints": {
    "appcustomizer-inject-css-application-customizer": {
      "chunks": [
        0
      ],
      "assets": [
        "appcustomizer-inject-css-application-customizer_03f3ca85ce1449817c76.js"
      ],
      "children": {},
      "childAssets": {}
    }
  },
  "namedChunkGroups": {
    "appcustomizer-inject-css-application-customizer": {
      "chunks": [
        0
      ],
      "assets": [
        "appcustomizer-inject-css-application-customizer_03f3ca85ce1449817c76.js"
      ],
      "children": {},
      "childAssets": {}
    }
  },
  "chunks": [
    {
      "id": 0,
      "rendered": true,
      "initial": true,
      "entry": true,
      "size": 2665,
      "names": [
        "appcustomizer-inject-css-application-customizer"
      ],
      "files": [
        "appcustomizer-inject-css-application-customizer_03f3ca85ce1449817c76.js"
      ],
      "hash": "8cb7ef051153f5910752",
      "siblings": [],
      "parents": [],
      "children": [],
      "childrenByOrder": {},
      "modules": [
        {
          "id": "GPet",
          "identifier": "external \"@microsoft/sp-application-base\"",
          "name": "external \"@microsoft/sp-application-base\"",
          "index": 1,
          "index2": 0,
          "size": 42,
          "built": true,
          "optional": false,
          "prefetched": false,
          "chunks": [
            0
          ],
          "issuer": "D:\\host\\MySPFx\\appcustomizer\\lib\\extensions\\appcustomizerInjectCss\\AppcustomizerInjectCssApplicationCustomizer.js",
          "issuerId": "P6WS",
          "issuerName": "./lib/extensions/appcustomizerInjectCss/AppcustomizerInjectCssApplicationCustomizer.js",
          "issuerPath": [
            {
              "id": "P6WS",
              "identifier": "D:\\host\\MySPFx\\appcustomizer\\lib\\extensions\\appcustomizerInjectCss\\AppcustomizerInjectCssApplicationCustomizer.js",
              "name": "./lib/extensions/appcustomizerInjectCss/AppcustomizerInjectCssApplicationCustomizer.js"
            }
          ],
          "failed": false,
          "errors": 0,
          "warnings": 0,
          "assets": [],
          "reasons": [
            {
              "moduleId": "P6WS",
              "moduleIdentifier": "D:\\host\\MySPFx\\appcustomizer\\lib\\extensions\\appcustomizerInjectCss\\AppcustomizerInjectCssApplicationCustomizer.js",
              "module": "./lib/extensions/appcustomizerInjectCss/AppcustomizerInjectCssApplicationCustomizer.js",
              "moduleName": "./lib/extensions/appcustomizerInjectCss/AppcustomizerInjectCssApplicationCustomizer.js",
              "type": "harmony side effect evaluation",
              "userRequest": "@microsoft/sp-application-base",
              "loc": "14:0-75"
            },
            {
              "moduleId": "P6WS",
              "moduleIdentifier": "D:\\host\\MySPFx\\appcustomizer\\lib\\extensions\\appcustomizerInjectCss\\AppcustomizerInjectCssApplicationCustomizer.js",
              "module": "./lib/extensions/appcustomizerInjectCss/AppcustomizerInjectCssApplicationCustomizer.js",
              "moduleName": "./lib/extensions/appcustomizerInjectCss/AppcustomizerInjectCssApplicationCustomizer.js",
              "type": "harmony import specifier",
              "userRequest": "@microsoft/sp-application-base",
              "loc": "48:2-27"
            }
          ],
          "usedExports": [
            "BaseApplicationCustomizer"
          ],
          "providedExports": null,
          "optimizationBailout": [
            "ModuleConcatenation bailout: Module is not an ECMAScript module"
          ],
          "depth": 1
        },
        {
          "id": "P6WS",
          "identifier": "D:\\host\\MySPFx\\appcustomizer\\lib\\extensions\\appcustomizerInjectCss\\AppcustomizerInjectCssApplicationCustomizer.js",
          "name": "./lib/extensions/appcustomizerInjectCss/AppcustomizerInjectCssApplicationCustomizer.js",
          "index": 0,
          "index2": 2,
          "size": 2581,
          "cacheable": true,
          "built": true,
          "optional": false,
          "prefetched": false,
          "chunks": [
            0
          ],
          "issuer": null,
          "issuerId": null,
          "issuerName": null,
          "issuerPath": null,
          "failed": false,
          "errors": 0,
          "warnings": 0,
          "assets": [],
          "reasons": [
            {
              "moduleId": null,
              "moduleIdentifier": null,
              "module": null,
              "moduleName": null,
              "type": "single entry",
              "userRequest": "D:\\host\\MySPFx\\appcustomizer\\lib\\extensions\\appcustomizerInjectCss\\AppcustomizerInjectCssApplicationCustomizer.js",
              "loc": "appcustomizer-inject-css-application-customizer"
            }
          ],
          "usedExports": true,
          "providedExports": [
            "default"
          ],
          "optimizationBailout": [
            "ModuleConcatenation bailout: Module is an entry point"
          ],
          "depth": 0,
          "source": "var __extends = (this && this.__extends) || (function () {\r\n    var extendStatics = function (d, b) {\r\n        extendStatics = Object.setPrototypeOf ||\r\n            ({ __proto__: [] } instanceof Array && function (d, b) { d.__proto__ = b; }) ||\r\n            function (d, b) { for (var p in b) if (b.hasOwnProperty(p)) d[p] = b[p]; };\r\n        return extendStatics(d, b);\r\n    };\r\n    return function (d, b) {\r\n        extendStatics(d, b);\r\n        function __() { this.constructor = d; }\r\n        d.prototype = b === null ? Object.create(b) : (__.prototype = b.prototype, new __());\r\n    };\r\n})();\r\nimport { BaseApplicationCustomizer } from '@microsoft/sp-application-base';\r\nimport * as $ from 'jquery';\r\nvar LOG_SOURCE = 'AppcustomizerInjectCssApplicationCustomizer';\r\n/** A Custom Action which can be run during execution of a Client Side Application */\r\nvar AppcustomizerInjectCssApplicationCustomizer = /** @class */ (function (_super) {\r\n    __extends(AppcustomizerInjectCssApplicationCustomizer, _super);\r\n    function AppcustomizerInjectCssApplicationCustomizer() {\r\n        return _super !== null && _super.apply(this, arguments) || this;\r\n    }\r\n    AppcustomizerInjectCssApplicationCustomizer.prototype.onInit = function () {\r\n        var cssUrl = this.properties.cssurl;\r\n        //console.log(cssUrl);\r\n        if (cssUrl) {\r\n            // inject the style sheet\r\n            var head = document.getElementsByTagName(\"head\")[0] || document.documentElement;\r\n            var customStyle = document.createElement(\"link\");\r\n            customStyle.href = cssUrl;\r\n            customStyle.rel = \"stylesheet\";\r\n            customStyle.type = \"text/css\";\r\n            head.insertAdjacentElement(\"beforeEnd\", customStyle);\r\n        }\r\n        $(document).ready(function () {\r\n            getHidedContent();\r\n            function getHidedContent() {\r\n                setTimeout(function () {\r\n                }, 5000);\r\n                //var elem = $('.ms-compositeHeader, div[role=\"header\"], div[data-automationid=\"SiteHeader\"], .ms-HubNav, .sp-App-hubNav:eq(1)').html();\r\n                $('.ms-compositeHeader, div[role=\"header\"], div[data-automationid=\"SiteHeader\"], .ms-HubNav, .sp-App-hubNav:eq(1)').removeClass('ms-HubNav');\r\n                //$('.ms-FocusZone').html(elem);\r\n            }\r\n        });\r\n        return Promise.resolve();\r\n    };\r\n    return AppcustomizerInjectCssApplicationCustomizer;\r\n}(BaseApplicationCustomizer));\r\nexport default AppcustomizerInjectCssApplicationCustomizer;\r\n//# sourceMappingURL=AppcustomizerInjectCssApplicationCustomizer.js.map"
        },
        {
          "id": "xeH2",
          "identifier": "external \"jquery\"",
          "name": "external \"jquery\"",
          "index": 2,
          "index2": 1,
          "size": 42,
          "built": true,
          "optional": false,
          "prefetched": false,
          "chunks": [
            0
          ],
          "issuer": "D:\\host\\MySPFx\\appcustomizer\\lib\\extensions\\appcustomizerInjectCss\\AppcustomizerInjectCssApplicationCustomizer.js",
          "issuerId": "P6WS",
          "issuerName": "./lib/extensions/appcustomizerInjectCss/AppcustomizerInjectCssApplicationCustomizer.js",
          "issuerPath": [
            {
              "id": "P6WS",
              "identifier": "D:\\host\\MySPFx\\appcustomizer\\lib\\extensions\\appcustomizerInjectCss\\AppcustomizerInjectCssApplicationCustomizer.js",
              "name": "./lib/extensions/appcustomizerInjectCss/AppcustomizerInjectCssApplicationCustomizer.js"
            }
          ],
          "failed": false,
          "errors": 0,
          "warnings": 0,
          "assets": [],
          "reasons": [
            {
              "moduleId": "P6WS",
              "moduleIdentifier": "D:\\host\\MySPFx\\appcustomizer\\lib\\extensions\\appcustomizerInjectCss\\AppcustomizerInjectCssApplicationCustomizer.js",
              "module": "./lib/extensions/appcustomizerInjectCss/AppcustomizerInjectCssApplicationCustomizer.js",
              "moduleName": "./lib/extensions/appcustomizerInjectCss/AppcustomizerInjectCssApplicationCustomizer.js",
              "type": "harmony side effect evaluation",
              "userRequest": "jquery",
              "loc": "15:0-28"
            },
            {
              "moduleId": "P6WS",
              "moduleIdentifier": "D:\\host\\MySPFx\\appcustomizer\\lib\\extensions\\appcustomizerInjectCss\\AppcustomizerInjectCssApplicationCustomizer.js",
              "module": "./lib/extensions/appcustomizerInjectCss/AppcustomizerInjectCssApplicationCustomizer.js",
              "moduleName": "./lib/extensions/appcustomizerInjectCss/AppcustomizerInjectCssApplicationCustomizer.js",
              "type": "harmony import specifier",
              "userRequest": "jquery",
              "loc": "35:8-9"
            },
            {
              "moduleId": "P6WS",
              "moduleIdentifier": "D:\\host\\MySPFx\\appcustomizer\\lib\\extensions\\appcustomizerInjectCss\\AppcustomizerInjectCssApplicationCustomizer.js",
              "module": "./lib/extensions/appcustomizerInjectCss/AppcustomizerInjectCssApplicationCustomizer.js",
              "moduleName": "./lib/extensions/appcustomizerInjectCss/AppcustomizerInjectCssApplicationCustomizer.js",
              "type": "harmony import specifier",
              "userRequest": "jquery",
              "loc": "41:16-17"
            }
          ],
          "usedExports": true,
          "providedExports": null,
          "optimizationBailout": [
            "ModuleConcatenation bailout: Module is not an ECMAScript module"
          ],
          "depth": 1
        }
      ],
      "filteredModules": 0,
      "origins": [
        {
          "module": "",
          "moduleIdentifier": "",
          "moduleName": "",
          "loc": "appcustomizer-inject-css-application-customizer",
          "request": "D:\\host\\MySPFx\\appcustomizer\\lib\\extensions\\appcustomizerInjectCss\\AppcustomizerInjectCssApplicationCustomizer.js",
          "reasons": []
        }
      ]
    }
  ],
  "modules": [
    {
      "id": "GPet",
      "identifier": "external \"@microsoft/sp-application-base\"",
      "name": "external \"@microsoft/sp-application-base\"",
      "index": 1,
      "index2": 0,
      "size": 42,
      "built": true,
      "optional": false,
      "prefetched": false,
      "chunks": [
        0
      ],
      "issuer": "D:\\host\\MySPFx\\appcustomizer\\lib\\extensions\\appcustomizerInjectCss\\AppcustomizerInjectCssApplicationCustomizer.js",
      "issuerId": "P6WS",
      "issuerName": "./lib/extensions/appcustomizerInjectCss/AppcustomizerInjectCssApplicationCustomizer.js",
      "issuerPath": [
        {
          "id": "P6WS",
          "identifier": "D:\\host\\MySPFx\\appcustomizer\\lib\\extensions\\appcustomizerInjectCss\\AppcustomizerInjectCssApplicationCustomizer.js",
          "name": "./lib/extensions/appcustomizerInjectCss/AppcustomizerInjectCssApplicationCustomizer.js"
        }
      ],
      "failed": false,
      "errors": 0,
      "warnings": 0,
      "assets": [],
      "reasons": [
        {
          "moduleId": "P6WS",
          "moduleIdentifier": "D:\\host\\MySPFx\\appcustomizer\\lib\\extensions\\appcustomizerInjectCss\\AppcustomizerInjectCssApplicationCustomizer.js",
          "module": "./lib/extensions/appcustomizerInjectCss/AppcustomizerInjectCssApplicationCustomizer.js",
          "moduleName": "./lib/extensions/appcustomizerInjectCss/AppcustomizerInjectCssApplicationCustomizer.js",
          "type": "harmony side effect evaluation",
          "userRequest": "@microsoft/sp-application-base",
          "loc": "14:0-75"
        },
        {
          "moduleId": "P6WS",
          "moduleIdentifier": "D:\\host\\MySPFx\\appcustomizer\\lib\\extensions\\appcustomizerInjectCss\\AppcustomizerInjectCssApplicationCustomizer.js",
          "module": "./lib/extensions/appcustomizerInjectCss/AppcustomizerInjectCssApplicationCustomizer.js",
          "moduleName": "./lib/extensions/appcustomizerInjectCss/AppcustomizerInjectCssApplicationCustomizer.js",
          "type": "harmony import specifier",
          "userRequest": "@microsoft/sp-application-base",
          "loc": "48:2-27"
        }
      ],
      "usedExports": [
        "BaseApplicationCustomizer"
      ],
      "providedExports": null,
      "optimizationBailout": [
        "ModuleConcatenation bailout: Module is not an ECMAScript module"
      ],
      "depth": 1
    },
    {
      "id": "I6O9",
      "identifier": "external \"@microsoft/sp-loader\"",
      "name": "external \"@microsoft/sp-loader\"",
      "index": null,
      "index2": null,
      "size": 42,
      "built": true,
      "optional": false,
      "prefetched": false,
      "chunks": [],
      "issuer": null,
      "issuerId": null,
      "issuerName": null,
      "issuerPath": null,
      "failed": false,
      "errors": 0,
      "warnings": 0,
      "assets": [],
      "reasons": [],
      "providedExports": null,
      "optimizationBailout": [
        "ModuleConcatenation bailout: Module is not an ECMAScript module"
      ],
      "depth": null
    },
    {
      "id": "P6WS",
      "identifier": "D:\\host\\MySPFx\\appcustomizer\\lib\\extensions\\appcustomizerInjectCss\\AppcustomizerInjectCssApplicationCustomizer.js",
      "name": "./lib/extensions/appcustomizerInjectCss/AppcustomizerInjectCssApplicationCustomizer.js",
      "index": 0,
      "index2": 2,
      "size": 2581,
      "cacheable": true,
      "built": true,
      "optional": false,
      "prefetched": false,
      "chunks": [
        0
      ],
      "issuer": null,
      "issuerId": null,
      "issuerName": null,
      "issuerPath": null,
      "failed": false,
      "errors": 0,
      "warnings": 0,
      "assets": [],
      "reasons": [
        {
          "moduleId": null,
          "moduleIdentifier": null,
          "module": null,
          "moduleName": null,
          "type": "single entry",
          "userRequest": "D:\\host\\MySPFx\\appcustomizer\\lib\\extensions\\appcustomizerInjectCss\\AppcustomizerInjectCssApplicationCustomizer.js",
          "loc": "appcustomizer-inject-css-application-customizer"
        }
      ],
      "usedExports": true,
      "providedExports": [
        "default"
      ],
      "optimizationBailout": [
        "ModuleConcatenation bailout: Module is an entry point"
      ],
      "depth": 0,
      "source": "var __extends = (this && this.__extends) || (function () {\r\n    var extendStatics = function (d, b) {\r\n        extendStatics = Object.setPrototypeOf ||\r\n            ({ __proto__: [] } instanceof Array && function (d, b) { d.__proto__ = b; }) ||\r\n            function (d, b) { for (var p in b) if (b.hasOwnProperty(p)) d[p] = b[p]; };\r\n        return extendStatics(d, b);\r\n    };\r\n    return function (d, b) {\r\n        extendStatics(d, b);\r\n        function __() { this.constructor = d; }\r\n        d.prototype = b === null ? Object.create(b) : (__.prototype = b.prototype, new __());\r\n    };\r\n})();\r\nimport { BaseApplicationCustomizer } from '@microsoft/sp-application-base';\r\nimport * as $ from 'jquery';\r\nvar LOG_SOURCE = 'AppcustomizerInjectCssApplicationCustomizer';\r\n/** A Custom Action which can be run during execution of a Client Side Application */\r\nvar AppcustomizerInjectCssApplicationCustomizer = /** @class */ (function (_super) {\r\n    __extends(AppcustomizerInjectCssApplicationCustomizer, _super);\r\n    function AppcustomizerInjectCssApplicationCustomizer() {\r\n        return _super !== null && _super.apply(this, arguments) || this;\r\n    }\r\n    AppcustomizerInjectCssApplicationCustomizer.prototype.onInit = function () {\r\n        var cssUrl = this.properties.cssurl;\r\n        //console.log(cssUrl);\r\n        if (cssUrl) {\r\n            // inject the style sheet\r\n            var head = document.getElementsByTagName(\"head\")[0] || document.documentElement;\r\n            var customStyle = document.createElement(\"link\");\r\n            customStyle.href = cssUrl;\r\n            customStyle.rel = \"stylesheet\";\r\n            customStyle.type = \"text/css\";\r\n            head.insertAdjacentElement(\"beforeEnd\", customStyle);\r\n        }\r\n        $(document).ready(function () {\r\n            getHidedContent();\r\n            function getHidedContent() {\r\n                setTimeout(function () {\r\n                }, 5000);\r\n                //var elem = $('.ms-compositeHeader, div[role=\"header\"], div[data-automationid=\"SiteHeader\"], .ms-HubNav, .sp-App-hubNav:eq(1)').html();\r\n                $('.ms-compositeHeader, div[role=\"header\"], div[data-automationid=\"SiteHeader\"], .ms-HubNav, .sp-App-hubNav:eq(1)').removeClass('ms-HubNav');\r\n                //$('.ms-FocusZone').html(elem);\r\n            }\r\n        });\r\n        return Promise.resolve();\r\n    };\r\n    return AppcustomizerInjectCssApplicationCustomizer;\r\n}(BaseApplicationCustomizer));\r\nexport default AppcustomizerInjectCssApplicationCustomizer;\r\n//# sourceMappingURL=AppcustomizerInjectCssApplicationCustomizer.js.map"
    },
    {
      "id": "xeH2",
      "identifier": "external \"jquery\"",
      "name": "external \"jquery\"",
      "index": 2,
      "index2": 1,
      "size": 42,
      "built": true,
      "optional": false,
      "prefetched": false,
      "chunks": [
        0
      ],
      "issuer": "D:\\host\\MySPFx\\appcustomizer\\lib\\extensions\\appcustomizerInjectCss\\AppcustomizerInjectCssApplicationCustomizer.js",
      "issuerId": "P6WS",
      "issuerName": "./lib/extensions/appcustomizerInjectCss/AppcustomizerInjectCssApplicationCustomizer.js",
      "issuerPath": [
        {
          "id": "P6WS",
          "identifier": "D:\\host\\MySPFx\\appcustomizer\\lib\\extensions\\appcustomizerInjectCss\\AppcustomizerInjectCssApplicationCustomizer.js",
          "name": "./lib/extensions/appcustomizerInjectCss/AppcustomizerInjectCssApplicationCustomizer.js"
        }
      ],
      "failed": false,
      "errors": 0,
      "warnings": 0,
      "assets": [],
      "reasons": [
        {
          "moduleId": "P6WS",
          "moduleIdentifier": "D:\\host\\MySPFx\\appcustomizer\\lib\\extensions\\appcustomizerInjectCss\\AppcustomizerInjectCssApplicationCustomizer.js",
          "module": "./lib/extensions/appcustomizerInjectCss/AppcustomizerInjectCssApplicationCustomizer.js",
          "moduleName": "./lib/extensions/appcustomizerInjectCss/AppcustomizerInjectCssApplicationCustomizer.js",
          "type": "harmony side effect evaluation",
          "userRequest": "jquery",
          "loc": "15:0-28"
        },
        {
          "moduleId": "P6WS",
          "moduleIdentifier": "D:\\host\\MySPFx\\appcustomizer\\lib\\extensions\\appcustomizerInjectCss\\AppcustomizerInjectCssApplicationCustomizer.js",
          "module": "./lib/extensions/appcustomizerInjectCss/AppcustomizerInjectCssApplicationCustomizer.js",
          "moduleName": "./lib/extensions/appcustomizerInjectCss/AppcustomizerInjectCssApplicationCustomizer.js",
          "type": "harmony import specifier",
          "userRequest": "jquery",
          "loc": "35:8-9"
        },
        {
          "moduleId": "P6WS",
          "moduleIdentifier": "D:\\host\\MySPFx\\appcustomizer\\lib\\extensions\\appcustomizerInjectCss\\AppcustomizerInjectCssApplicationCustomizer.js",
          "module": "./lib/extensions/appcustomizerInjectCss/AppcustomizerInjectCssApplicationCustomizer.js",
          "moduleName": "./lib/extensions/appcustomizerInjectCss/AppcustomizerInjectCssApplicationCustomizer.js",
          "type": "harmony import specifier",
          "userRequest": "jquery",
          "loc": "41:16-17"
        }
      ],
      "usedExports": true,
      "providedExports": null,
      "optimizationBailout": [
        "ModuleConcatenation bailout: Module is not an ECMAScript module"
      ],
      "depth": 1
    }
  ],
  "filteredModules": 0,
  "logging": {
    "webpack.buildChunkGraph.visitModules": {
      "entries": [],
      "filteredEntries": 2,
      "debug": false
    }
  },
  "children": []
}